collimator/VERSION
collimator/__init__.py
collimator/__main__.py
collimator/config.py
collimator/controllers.py
collimator/icon.png
collimator/indi_client.py
collimator/indi_thread.py
collimator/main.py
collimator/markers.py
collimator/utils.py
collimator/welcome.png
collimator/widgets.py
collimator/windows.py
Collimator-0.1.2.dist-info/METADATA
Collimator-0.1.2.dist-info/WHEEL
Collimator-0.1.2.dist-info/top_level.txt
Collimator-0.1.2.dist-info/RECORD
