Metadata-Version: 2.1
Name: Collimator
Version: 0.1.2
Summary: Electronic collimator for your telescope
Home-page: http://github.com/wlatanowicz/collimator
Author: Wiktor Latanowicz
Author-email: collimator@wiktor.latanowicz.com
License: MIT
Platform: UNKNOWN
Classifier: Programming Language :: Python :: 3
Classifier: License :: OSI Approved :: MIT License
Classifier: Operating System :: OS Independent
Requires-Python: >=3.6
Requires-Dist: pip (>=22.0.4)
Requires-Dist: Pillow (>=9.0.1)
Requires-Dist: indipy (>=0.2.2)
Requires-Dist: astropy (>=5.0.1)
Requires-Dist: appdirs (>=1.4.4)
Requires-Dist: PyQt6 (>=6.2.3)
